{"R":["0457"],"INC":["Ha ki rövideden akarsz komédiát, íme"],"TITRE":["Commendatiuncula brevis comoediae"],"AUT":[{"1":"Szegedi","2":"Lőrinc"}],"TRAD":["1"],"AN":["1571"],"PREC":["1"],"CHANS":["1"],"SIGNE":["5"],"MOI":["2"],"GENR":["90"],"GENRE":["048,050,053,061,090"],"COLO":["2"],"DEDIE":["Báthory Miklós, Losonczy Fruzsina"],"ACR":["2"],"COMMENT":["Év: Horváth János: 1571. márc. 14. és május 25. között írhatta, az ajánlás tartalma miatt lehet erre következtetni."],"INT":["1"],"LON":["10"],"PRE":["2"],"TYPME":["7"],"REL":[{"r":"1"}],"RMNY":["28:0359    P:"],"ED-CR":["RMDE-1-723"],"RECTYP":["0"],"$MFN":["424"]}