{"R":["3005"],"INC":["Süly, itt teneked nem kellett volna kelned"],"TITRE":["Contra de fistula seu süly"],"TRAD":["3"],"AN":["1511-1526"],"PREC":["5"],"CHANS":["1"],"SIGNE":["2"],"GENRE":["001,003,123"],"COLO":["2"],"ACR":["2"],"COMMENT":["Szapolyai János bájoló imája: \"Sőly! Itt te neked nem kellett volna kelned. Uram Isten! Sőly! Én téged átkozlak Atyának és Fiúnak és Szentléleknek átkával, Atyának haragjával. Sőly! Én téged átkozlak Atyának és Fiúnak és Szentléleknek átkával; és haragjának Szentháromságnak. Innét elvesszél. Szent Gracias pispek itt ne leljen. Hetvenhét féle sőly! Sem fővel ... sem szívvellek, sem bájollak, de idvezlek Istennek szent keresztfájával, Boldog Asszonynak szent szüle tejével, Szentháromság innét elvezessen, szent Illés próféta itt ne találjon, Ámen.\""],"INT":["1"],"LON":["1"],"PRE":["3"],"TYPME":["11"],"REL":[{"k":"1"}],"MKÉVB":["19:0807    P:"],"ED-CR":["Könyvtári Szemle-1971-78, 80"],"FACS":["Könyvtári Szemle-1971-78"],"RECTYP":["0"],"$MFN":["1582"]}