{"R":["1287"],"INC":["Sokat szóltam immár nektek Szentírásból"],"TITRE":["Szent Pál apostol életéről és haláláról szép história"],"AUT":[{"1":"Ilosvai Selymes","2":"Péter"}],"TRAD":["2"],"TITOR":["Act 9-28"],"AN":["1564"],"PREC":["1"],"CHANS":["2"],"SIGNE":["1"],"MOI":["2"],"GENR":["9"],"GENRE":["001,002,004,009"],"COLO":["1"],"DONCOLO":[{"1":"Nem csuda ha vétek vagyon az írásban, Sok reszelő, fúró kárt tett nékem írásban ... Ilosvai Péter deák bánatjában, Evvel vigasztalván szívét szomorúságban","L":"nemes Szakmárban, Egy jámbor lakatgyártónak házában","d":"Ezerötszáz és az hatvannégy esztendőben, Hideglelő Kisasszonnak havában"}],"ACR":["1"],"ACROST":["SERICEEVS PETRVS ILOOSVANVS L SVA SEREITIV COMMENDAT OMNIBVS CHRISTIANIS [IRAFTHMEAET] / ILOSVANVS SERICEVS PETRVS OMNIBVS PIETATEM PROOOIITENTIBVS ET DEVM TIMANTIBVS SVA COMMENDAT VOBIS OFFITAA / HACTENVSVNDOSAM PEVLI DEESKRIBERE VITAM COEPIMVS INDE SVAM ET AVDI PREFERRE NECEM"],"DONACR":[{"1":"Iloosvanvs Sericeevs","2":"Petrvs"},{"1":"Ilosvanvs Sericevs","2":"Petrvs"}],"INT":["1"],"LON":["272","273"],"PRE":["1"],"TYPME":["1"],"METR":["A 12 6 6","A 12 6 6","A 12 6 6","A 13 6 7"],"RIME":["AAAA"],"SYLL":["12121213"],"REL":[{"p":"5"}],"RMNY":["28:0265    P:","28:0339/A  P:","28:0381    P:","28:0438    P:","28:0610    P:"],"ED-MEL":["RMDT1  15SZ"],"ED-CR":["RMKT-4-173"],"DAL-MOD":["1015","1365","1420"],"RECTYP":["0"],"$MFN":["1183"]}