{"R":["1285"],"INC":["Sokat szólhatok a meglett dolgokról"],"TITRE":["Judit asszony históriája"],"AUT":[{"1":"Tinódi","2":"Sebestyén"}],"TRAD":["2"],"TITOR":["Iud 1-15"],"AN":["1540"],"PREC":["4"],"CHANS":["2"],"SIGNE":["1"],"MOI":["2"],"GENR":["9"],"GENRE":["001,002,004,009"],"COLO":["1"],"DONCOLO":[{"1":"Tinódi Sebestyén deák","L":"Anthimus Szigetben, ... Terek Bálintnak házánál éltében"}],"ACR":["1"],"ACROST":["SEBASTIANVS LITERATVS DE TINOD IN LINGVA HVNGARICA ECS BIBLIA CANENDVM CONVERTOeNS BELLVM HVNGARICVM POeRSCRVTANS FEKIT"],"DONACR":[{"1":"Tinod","2":"Sebastianvs Literatvs de"}],"INT":["1"],"LON":["104"],"PRE":["1"],"TYPME":["1"],"METR":["A 11 4 4 3","A 11 4 4 3","A 11 4 4 3","A 11 4 4 3"],"RIME":["AAAA"],"SYLL":["11111111"],"REL":[{"v":"1"}],"RMNY":["28:0109    P:00f4-A"],"ED-MEL":["RMDT1  31SZ"],"ED-CR":["RMKT-3-237"],"RECTYP":["0"],"$MFN":["1181"]}