{"R":["0574"],"INC":["Ím, egy szép históriát mostan mondok"],"TITRE":["Jeruzsálem veszedelméről"],"AUT":[{"1":"Szegedi","2":"András"}],"TRAD":["2"],"TITOR":["De bello Iudaico, 6-7"],"AUTET":[{"1":"Rufinus Tyrannius (Aquiliensis)"}],"AN":["1553"],"PREC":["1"],"CHANS":["2"],"SIGNE":["1"],"MOI":["2"],"GENR":["68"],"GENRE":["048,049,051,056,068"],"COLO":["1"],"DEDIE":["Egy úrfinak az ő nagy örömében"],"DONCOLO":[{"1":"Ezt ki szörzé, gondolkodék magában, Bánkódik, mert nincsen pénz tassolyában, Vagyon azért ő is nagy gondolatban, Nem tud melyfelé váltani útában. Gyönyörűséges napját mert megvárja, Ura tisztességén magát mutatja, De azután magában azt forgatja, Többé immár ő ez földet nem lakja. Soha többé Telegden ő nem lakik, Kurta Koppán halában ő sem eszik, Ha pénzzel, szép szóval őt nem enyhítik, Mert erszénye naponként üresedik","d":"Ezerötszáz és az ötvenháromban","L":"Telegden ... Kurta Koppán ... Sebes-Körösnek el alá mentiben"}],"ACR":["1"],"ACROST":["IOSEPHI IVDEI COGNOMEENTO FLVII VIRI CLARISSIMI HISTORIOGRAPHI DE BLLO IVDAIO COMMISSO CVM ROMANIS VT EEERSIONE VRBIS VLTIMA IEROSOLIMORVM TITO ET VESPASIANO INPERANTIBVS E GRECO IN LATINVM PER RVFFINOM AKVILIIENSENM INTERPRETAM TRANSLATVM PER ANDREAM CHEGEDII FACTA IN HVNGARICVM IDIIMA E LATINO TRADVCTVAM"],"COMMENT":["Dedikáció: egy úrfi = Telegdi-család egyik tagja."],"INT":["1"],"LON":["273","274","275","276"],"PRE":["1"],"TYPME":["1"],"METR":["A 11","A 11","A 11","A 11"],"RIME":["AAAA"],"SYLL":["11111111"],"REL":[{"p":"1","v":"5"}],"RMNY":["28:0345    P:","28:0382    P:","28:0465    P:","28:0511    P:"],"MKÉVB":["18:0001    P:0006-A","18:0032/2  P:0012-A"],"ED-MEL":["RMDT1 752","RMDT1 753"],"ED-CR":["RMKT-6-153"],"DAL-MOD":["0057","0957"],"RECTYP":["0"],"$MFN":["532"]}