{"R":["0810"],"INC":["Krisztus, mi édes Megváltónk"],"TITRE":["Hymnus a Megváltóról"],"TRAD":["2"],"INCOR":["Christe, Redemptor omnium"],"AN":["1574"],"PREC":["2"],"CHANS":["2"],"SIGNE":["2"],"MOI":["2"],"GENR":["16"],"GENRE":["001,003,008,016"],"COLO":["2"],"ACR":["2"],"COMMENT":["Madas Edit: A szöveg folytatása nem egyezik a latinnal, bár Huszár Gál maga utal rá. Csomasz Tóth Kálmán: \"A nótajelzésben megadott latin himnusz meglehetsen szabad verziója.\""],"INT":["1"],"LON":["7"],"PRE":["1"],"TYPME":["1"],"METR":["X  8","X  8","X  8","X  8"],"RIME":["XXXX"],"SYLL":[" 8 8 8 8"],"REL":[{"e":"1"}],"RMNY":["28:0353/1  P:sss3-A"],"ED-MEL":["RMDT1 163SZ","NZ-3-154"],"DAL-CON":["5031"],"RECTYP":["0"],"$MFN":["743"]}