{"R":["1218"],"INC":["Semmiből teremté az Úristen az embert"],"TITRE":["Karácsonyi ének"],"AUT":[{"1":"Sztárai","2":"Mihály"}],"TRAD":["3"],"AN":["1574"],"PREC":["2"],"CHANS":["2"],"SIGNE":["1"],"MOI":["2"],"GENR":["36"],"GENRE":["001,003,025,036"],"COLO":["2"],"ACR":["1"],"ACROST":["STARINVS"],"DONACR":[{"1":"Starinvs"}],"INT":["1"],"LON":["7","8"],"PRE":["1"],"TYPME":["1"],"METR":["A 15 6 9","A 11 4 7","A  8 4 4"],"RIME":["AAA"],"SYLL":["1511 8"],"REL":[{"r":"3","e":"6","p":"5"}],"RMNY":["28:0353/1  P:0191-B","28:0513    P:0014-A","28:0713    P:0054","28:0965    P:0013","28:1107/1  P:0100-A","28:1205/1  P:0094-A","28:1523/1  P:0094-A","28:1628/1  P:0202","29:0698    P:0096","29:0726    P:0081","29:0890/2  P:0149","29:1183/2  P:0206"],"MKÉVB":["18:0058    P:0347","18:0082/1  P:0150"],"ED-MEL":["RMDT1 140SZ"],"ED-CR":["RMKT-5-108"],"DAL-CON":["5133","5132","1444"],"RECTYP":["0"],"$MFN":["1114"]}