{"R":["0342"],"INC":["Ember, emlékezzél végedről"],"TITRE":["Keresztyéni panaszolkodás és intés"],"AUT":[{"1":"Heltai","2":"Gáspár"}],"TRAD":["2"],"TITOR":["Trostbüchlein"],"AUTET":[{"1":"Spangenberg","2":"Johann"}],"AN":["1553"],"PREC":["2"],"CHANS":["2"],"SIGNE":["5"],"MOI":["2"],"GENR":["47","132"],"GENRE":["001,003,025,101","001,003,025,047"],"COLO":["2"],"ACR":["2"],"INT":["1"],"LON":["18"],"PRE":["1"],"TYPME":["1"],"METR":["A  9 4 5","A  9 4 5"],"RIME":["AA"],"SYLL":[" 9 9"],"REL":[{"e":"1"}],"RMNY":["28:0102    P:00A5-B"],"ED-CR":["RMKT-6-108"],"RECTYP":["0"],"$MFN":["313"]}