{"R":["0428"],"INC":["Gyalu várban kínjaiban, szerzette kilencvennégyben (explicit)"],"TITRE":["Rabének"],"AUT":[{"1":"Báthory","2":"Boldizsár"}],"TRAD":["1"],"AN":["1594"],"PREC":["1"],"CHANS":["2"],"SIGNE":["1"],"MOI":["1"],"GENR":["38","260"],"GENRE":["001,003,025,260","001,003,025,038"],"COLO":["1"],"DONCOLO":[{"1":"Báthory Boldizsár bánatjában, ... kínjaiban","d":"kilencvennégyben","L":"Gyalu várban"}],"ACR":["3"],"ACROST":["FEREN LAMEEE"],"INT":["2"],"LON":["11"],"PRE":["1"],"TYPME":["1"],"METR":["A  8 4 4","A  8 4 4","A  8 4 4","A  8 4 4"],"RIME":["AAAA"],"SYLL":[" 8 8 8 8"],"REL":[{"v":"1"}],"MKÉVB":["18:0047    P:0096-A"],"ED-CR":["RMKT17-1-30"],"RECTYP":["0"],"$MFN":["395"]}