{"R":["0554"],"INC":["Hozzád kiált lelkem, örök életemnek Istene"],"TITRE":["Vitézi ének és könyörgés"],"AUT":[{"1":"Homonnai Drugeth","2":"István"}],"TRAD":["1"],"AN":["1598"],"PREC":["2"],"CHANS":["2"],"SIGNE":["1"],"MOI":["1"],"GENR":["38","86"],"GENRE":["048,050,053,058,086","001,003,025,038"],"COLO":["2"],"ACR":["1"],"ACROST":["HOMONNAI ISTVAN"],"DONACR":[{"1":"Homonnai","2":"Istvan"}],"INT":["1"],"LON":["15"],"PRE":["1"],"TYPME":["1"],"METR":["A 19 6 6 7","A 19 6 6 7","A 19 6 6 7"],"RIME":["AAA"],"SYLL":["191919"],"REL":[{"v":"1"}],"MKÉVB":["18:0043    P:0001"],"ED-CR":["RMKT17-1-20"],"RECTYP":["0"],"$MFN":["512"]}