{"R":["0972"],"INC":["Mindeneknek teremtője és híveknek megváltója ... hallgasd meg"],"TITRE":["Adventi hymnus"],"TRAD":["2"],"INCOR":["Conditor alme siderum, aeterna lux credentium"],"TITOR":["In Dominicis Adventus ad Vesperas hymnus"],"HYMNUS":["AH,51,46","CH,3733","CH,3734"],"AN":["1574"],"PREC":["2"],"CHANS":["2"],"SIGNE":["2"],"MOI":["2"],"GENR":["16"],"GENRE":["001,003,008,016"],"COLO":["2"],"ACR":["2"],"INT":["1"],"LON":["7"],"PRE":["1"],"TYPME":["1"],"METR":["X  8","X  8","X  8","X  8"],"RIME":["XXXX"],"SYLL":[" 8 8 8 8"],"REL":[{"p":"3","e":"2"}],"RMNY":["28:0353/1  P:0142-B"],"MKÉVB":["18:0038    P:0009-B","18:0041    P:0001","18:0057    P:0025-A","18:0062    P:0003-B"],"ED-MEL":["RMDT1  78SZ","RMDT1  79SZ","NZ-3-149"],"DAL-CON":["5037"],"RECTYP":["0"],"VIDE":["0227","0555"],"$MFN":["892"]}