{"R":["3211"],"INC":["Krisztus feltámada menten nagy kínjából"],"TITRE":["Húsvéti népének"],"TRAD":["2"],"INCOR":["Christus surrexit, mala nostra texit"],"LANOR":["lat"],"AN":["1401-1450"],"PREC":["6"],"CHANS":["2"],"SIGNE":["2"],"GENR":["200"],"GENRE":["001,003,008,200"],"COLO":["3"],"ACR":["3"],"COMMENT":["Refrén a strófák között. (Összesen 1 strófás!?)"],"INT":["2"],"LON":["1"],"PRE":["1"],"TYPME":["1"],"METR":["X  6","X  7","A  7","A  7","X  4"],"RIME":["XXAAX"],"SYLL":[" 6 7 7 7 4"],"REL":[{"k":"1"}],"MKÉVB":["19:0759    P:0003-B"],"ED-CR":["NZ-1-65"],"FACS":["Népzene és Zenetörténet I-1972-72"],"RECTYP":["0"],"VIDE":["0790"],"REFRÉN":["--------R0"],"$MFN":["1446"]}