{"R":["0213"],"INC":["Bűnnek az ő zsoldja a halál, jól tudjuk"],"TITRE":["Temetési dicséret"],"AUT":[{"1":"Bereki","2":"István","3":"?"}],"TRAD":["3"],"AN":["1600"],"PREC":["2"],"CHANS":["2"],"SIGNE":["1"],"MOI":["2"],"GENR":["35"],"GENRE":["001,003,024,035"],"COLO":["2"],"ACR":["1"],"ACROST":["BEREKINVS PLORAT"],"DONACR":[{"1":"Berekinvs"}],"COMMENT":["Metr.: az 1.-2. és a 17.-18. versszakban (a 18 versszakosoknál) nincs refrén, ezt hogy lehet feltüntetni? Esetleg R*."],"INT":["1"],"LON":["16","18","19"],"PRE":["1"],"TYPME":["1"],"METR":["A 12 6 6","A 12 6 6","A 12 6 6","A 12 6 6"],"RIME":["AAAA"],"SYLL":["12121212"],"REL":[{"k":"3","p":"11","e":"3","v":"1","r":"1","u":"2"}],"RMNY":["28:1438    P:0533","28:1628/4  P:0041","29:0698    P:0792","29:0713    P:0379-B","29:0726    P:0694","29:0890/2  P:0317","29:0897    P:0042","29:0956    P:0014","29:1183/2  P:0470","29:1188    P:0680","29:1288/A  P:0132","29:1408/A  P:","29:1425/A  P:0186","29:1446/2  P:0121","29:1504    P:0012","29:1618/P  P:0182"],"MKÉVB":["18:0071/2  P:0002-A","18:0088    P:0005-B","18:0115    P:0099-A","18:0128    P:0008-B","18:0178    P:0614"],"ED-MEL":["RMDT2 129SZ","RMDT2 302SZ"],"DAL-MOD":["1478"],"RECTYP":["0"],"REFRÉN":["------R2"],"$MFN":["198"]}